tests/__init__.py
tests/any.py
tests/conftest.py
tests/httpbin.py
tests/kafka.py
tests/test_cli.py
tests/test_repository.py
tests/test_stream_topic.py
tests/test_url_probe.py
website_monitor/__init__.py
website_monitor/cli.py
website_monitor/env.py
website_monitor/repository.py
website_monitor/stats.py
website_monitor/streamtopic.py
website_monitor/url_probe.py
wm-0.0.6.dist-info/LICENSE
wm-0.0.6.dist-info/METADATA
wm-0.0.6.dist-info/WHEEL
wm-0.0.6.dist-info/entry_points.txt
wm-0.0.6.dist-info/top_level.txt
wm-0.0.6.dist-info/RECORD
